Seven_segment.v
module Seven_segment(input [15:0] producto , input clk , rst  , output reg [6:0] LED_out , output reg d0 , d1 , d2 ,d3);


reg [1:0] state , next_state;
parameter s3 = 2'b11, s2 = 2'b10, s1 = 2'b01, s0 = 2'b00;


//next state logic 

always @ (*) begin

case(state)
  s0: next_state = s1;
  s1: next_state = s2;
  s2: next_state = s3;
  s3: next_state = s0;
endcase
end



always @(posedge clk , posedge rst )
begin

  if (rst) 
     state <= s0;
 else 
    state <= next_state;
    
end




always @(*) begin

    case(state)

    s0: begin
        d0=1; d1 =0 ; d2=0 ; d3 =0;

        case(producto[3:0])

        4'b0000: LED_out = 7'b0000001; // "0"     
        4'b0001: LED_out = 7'b1001111; // "1" 
        4'b0010: LED_out = 7'b0010010; // "2" 
        4'b0011: LED_out = 7'b0000110; // "3" 
        4'b0100: LED_out = 7'b1001100; // "4" 
        4'b0101: LED_out = 7'b0100100; // "5" 
        4'b0110: LED_out = 7'b0100000; // "6" 
        4'b0111: LED_out = 7'b0001111; // "7" 
        4'b1000: LED_out = 7'b0000000; // "8"     
        4'b1001: LED_out = 7'b0000100; // "9" 
        4'b1010: LED_out = 7'b0001000; // "A" 
        4'b1011: LED_out = 7'b0000000; // "B" 
        4'b1100: LED_out = 7'b0110001; // "C"
        4'b1101: LED_out = 7'b0000001; // "D"
        4'b1110: LED_out = 7'b0110000; // "E"
        4'b1111: LED_out = 7'b0111000; // "F"    



        endcase
    end
    s1:begin
         d0=0; d1 =1 ; d2=0 ; d3 =0;

        case(producto[7:4])

        4'b0000: LED_out = 7'b0000001; // "0"     
        4'b0001: LED_out = 7'b1001111; // "1" 
        4'b0010: LED_out = 7'b0010010; // "2" 
        4'b0011: LED_out = 7'b0000110; // "3" 
        4'b0100: LED_out = 7'b1001100; // "4" 
        4'b0101: LED_out = 7'b0100100; // "5" 
        4'b0110: LED_out = 7'b0100000; // "6" 
        4'b0111: LED_out = 7'b0001111; // "7" 
        4'b1000: LED_out = 7'b0000000; // "8"     
        4'b1001: LED_out = 7'b0000100; // "9" 
        4'b1010: LED_out = 7'b0001000; // "A" 
        4'b1011: LED_out = 7'b0000000; // "B" 
        4'b1100: LED_out = 7'b0110001; // "C"
        4'b1101: LED_out = 7'b0000001; // "D"
        4'b1110: LED_out = 7'b0110000; // "E"
        4'b1111: LED_out = 7'b0111000; // "F"    



        endcase
     end   
    s2:begin
        d0=0; d1 =0 ; d2=1 ; d3 =0;

        case(producto[11:8])

        4'b0000: LED_out = 7'b0000001; // "0"     
        4'b0001: LED_out = 7'b1001111; // "1" 
        4'b0010: LED_out = 7'b0010010; // "2" 
        4'b0011: LED_out = 7'b0000110; // "3" 
        4'b0100: LED_out = 7'b1001100; // "4" 
        4'b0101: LED_out = 7'b0100100; // "5" 
        4'b0110: LED_out = 7'b0100000; // "6" 
        4'b0111: LED_out = 7'b0001111; // "7" 
        4'b1000: LED_out = 7'b0000000; // "8"     
        4'b1001: LED_out = 7'b0000100; // "9" 
        4'b1010: LED_out = 7'b0001000; // "A" 
        4'b1011: LED_out = 7'b0000000; // "B" 
        4'b1100: LED_out = 7'b0110001; // "C"
        4'b1101: LED_out = 7'b0000001; // "D"
        4'b1110: LED_out = 7'b0110000; // "E"
        4'b1111: LED_out = 7'b0111000; // "F"    



        endcase
        end
    s3:begin
         d0=0; d1 =0 ; d2=0 ; d3 =1;

        case(producto[15:12])

        4'b0000: LED_out = 7'b0000001; // "0"     
        4'b0001: LED_out = 7'b1001111; // "1" 
        4'b0010: LED_out = 7'b0010010; // "2" 
        4'b0011: LED_out = 7'b0000110; // "3" 
        4'b0100: LED_out = 7'b1001100; // "4" 
        4'b0101: LED_out = 7'b0100100; // "5" 
        4'b0110: LED_out = 7'b0100000; // "6" 
        4'b0111: LED_out = 7'b0001111; // "7" 
        4'b1000: LED_out = 7'b0000000; // "8"     
        4'b1001: LED_out = 7'b0000100; // "9" 
        4'b1010: LED_out = 7'b0001000; // "A" 
        4'b1011: LED_out = 7'b0000000; // "B" 
        4'b1100: LED_out = 7'b0110001; // "C"
        4'b1101: LED_out = 7'b0000001; // "D"
        4'b1110: LED_out = 7'b0110000; // "E"
        4'b1111: LED_out = 7'b0111000; // "F"    



        endcase
    end

    endcase



end
endmodule

Seven_segment_tb.v

module Seven_segment_tb;

    // Inputs
    reg [15:0] producto;
    reg clk;
    reg rst;

    // Outputs
    wire [6:0] LED_out;
    wire d0, d1, d2, d3;

    // Instantiate the Unit Under Test (UUT)
    Seven_segment uut (
        .producto(producto), 
        .clk(clk), 
        .rst(rst), 
        .LED_out(LED_out), 
        .d0(d0), 
        .d1(d1), 
        .d2(d2), 
        .d3(d3)
    );

    // Clock generation
    initial begin
        clk = 0;
        forever #5 clk = ~clk; // Toggle clock every 10 ns
    end

    // Test cases
    initial begin
          $dumpfile("seven.vcd ");
        $dumpvars(0, Seven_segment_tb);
     
        rst = 1;
        producto = 16'h123F; 
        #10;
        rst = 0;
        #100;               
        $finish;
    end

 

endmodule

.vcd
$date
	Wed Nov 22 12:44:18 2023
$end
$version
	Icarus Verilog
$end
$timescale
	1s
$end
$scope module Seven_segment_tb $end
$var wire 1 ! d3 $end
$var wire 1 " d2 $end
$var wire 1 # d1 $end
$var wire 1 $ d0 $end
$var wire 7 % LED_out [6:0] $end
$var reg 1 & clk $end
$var reg 16 ' producto [15:0] $end
$var reg 1 ( rst $end
$scope module uut $end
$var wire 1 & clk $end
$var wire 16 ) producto [15:0] $end
$var wire 1 ( rst $end
$var reg 7 * LED_out [6:0] $end
$var reg 1 $ d0 $end
$var reg 1 # d1 $end
$var reg 1 " d2 $end
$var reg 1 ! d3 $end
$var reg 2 + next_state [1:0] $end
$var reg 2 , state [1:0] $end
$upscope $end
$upscope $end
$enddefinitions $end
#0
$dumpvars
b0 ,
b1 +
b111000 *
b1001000111111 )
1(
b1001000111111 '
0&
b111000 %
1$
0#
0"
0!
$end
#5
1&
#10
0&
0(
#15
b110 %
b110 *
1#
0$
b10 +
b1 ,
1&
#20
0&
#25
b10010 %
b10010 *
1"
0#
b11 +
b10 ,
1&
#30
0&
#35
b1001111 %
b1001111 *
1!
0"
b0 +
b11 ,
1&
#40
0&
#45
b111000 %
b111000 *
0!
1$
b1 +
b0 ,
1&
#50
0&
#55
b110 %
b110 *
1#
0$
b10 +
b1 ,
1&
#60
0&
#65
b10010 %
b10010 *
1"
0#
b11 +
b10 ,
1&
#70
0&
#75
b1001111 %
b1001111 *
1!
0"
b0 +
b11 ,
1&
#80
0&
#85
b111000 %
b111000 *
0!
1$
b1 +
b0 ,
1&
#90
0&
#95
b110 %
b110 *
1#
0$
b10 +
b1 ,
1&
#100
0&
#105
b10010 %
b10010 *
1"
0#
b11 +
b10 ,
1&
