memory_calculations.v
module memo(
        input logic clk , rst ,
        input logic [31:0] a, 
        output  reg [15:0] ra,
        output reg [15:0] rb 

    );
        logic [32:0] RAM[20:0];
        integer i;
        initial begin
            $readmemh("calculations.dat", RAM);
            
        end

    always  @(*)
    begin

           // ra=RAM[31:16][a];
            //rb=RAM[15:0][a];
    end



endmodule


module button_counter(output reg [15:0] producto, input   clk , rst  , NEXT);

reg [2:0] state , next_state;
reg [32:0] counter;
parameter hold =2'b00 , pressed_buttom = 2'b01 , released_buttom = 2'b10;
reg [15:0] A , B ;


always @*
begin

case(state)

hold: begin
    if(NEXT) next_state = pressed_buttom;
    else next_state = hold;
end
pressed_buttom :  begin
    if(!NEXT) next_state = released_buttom;
    else next_state = pressed_buttom;
    end
released_buttom: begin
    if(NEXT) next_state = hold;
else next_state = released_buttom;
end
endcase



end



always @(posedge clk , posedge rst)
begin

if(rst) begin
 counter<=0;
 state<=hold;
end
else begin
state<=next_state;
if(state== pressed_buttom && next_state == released_buttom)
 counter<=counter+1;
  

end


end



endmodule

calculations_tb.v

module button_counter_tb;

    // Entradas
    reg clk;
    reg rst;
    reg NEXT;

    // Salidas
    wire [15:0] producto;

    // Instancia del módulo a probar
    button_counter uut (
        .producto(producto), 
        .clk(clk), 
        .rst(rst), 
        .NEXT(NEXT)
    );

    // Generación de la señal de reloj
    initial begin
        clk = 0;
        forever #10 clk = ~clk; // Cambia el estado cada 10 ns
    end

    // Proceso de prueba
    initial begin
        $dumpfile("counter.vcd");
        $dumpvars(0,button_counter_tb);
        // Inicialización
        rst = 1;
        NEXT = 0;

        // Reinicio del sistema
        #20;
        rst = 0;

        // Simula el botón presionado
        #30 NEXT = 1;
        #20 NEXT = 0;

        // Simula el botón presionado de nuevo
        #40 NEXT = 1;
        #20 NEXT = 0;

        // Simula el botón presionado una vez más
        #50 NEXT = 1;
        #20 NEXT = 0;

        // Finaliza la simulación
        #100 $finish;
    end
      
endmodule

counter.vcd
$date
	Thu Nov 23 11:53:03 2023
$end
$version
	Icarus Verilog
$end
$timescale
	1s
$end
$scope module button_counter_tb $end
$var wire 16 ! producto [15:0] $end
$var reg 1 " NEXT $end
$var reg 1 # clk $end
$var reg 1 $ rst $end
$scope module uut $end
$var wire 1 " NEXT $end
$var wire 1 # clk $end
$var wire 1 $ rst $end
$var reg 33 % counter [32:0] $end
$var reg 3 & next_state [2:0] $end
$var reg 16 ' producto [15:0] $end
$var reg 3 ( state [2:0] $end
$upscope $end
$upscope $end
$enddefinitions $end
#0
$dumpvars
b0 (
bx '
b0 &
b0 %
1$
0#
0"
bx !
$end
#10
1#
#20
0#
0$
#30
1#
#40
0#
#50
b1 (
b1 &
1#
1"
#60
0#
#70
b1 %
b10 (
b10 &
1#
0"
#80
0#
#90
1#
#100
0#
#110
b0 (
b1 &
1#
1"
#120
0#
#130
b0 &
1#
0"
#140
0#
#150
1#
#160
0#
#170
1#
#180
b1 &
0#
1"
#190
b1 (
1#
#200
b10 &
0#
0"
#210
b10 %
b10 (
1#
