memory_calculations.v


module memo(
        input logic clk , rst ,
        input logic [31:0] a, 
        output  reg [15:0] ra,
        output reg [15:0] rb 

    );
        logic [32:0] RAM[20:0];
        integer i;
        initial begin
            $readmemh("calculations.dat", RAM);
            
        end

    always  @(*)
    begin

            ra=RAM[a][31:16];
            rb=RAM[a][15:0];
    end



endmodule

module Fp_clasifier
(input [15:0] float , 
output snan , qnan , inf , zero , subnormal , normal );

wire expOnes , expZeroes , sigZeroes ; 

assign expOnes = &float[14:10];
assign expZeroes = ~|float[14:10];
assign sigZeroes = ~|float[9:0];

assign snan = expOnes & ~sigZeroes & ~float[9];
assign qnan = expOnes & float[9];
assign inf  = expOnes & sigZeroes;
assign zero = expZeroes & sigZeroes;
assign subnormal = expZeroes & ~sigZeroes;
assign normal = ~expOnes &  ~expZeroes;

endmodule

module FP_mul(output wire [15:0] producto, input [15:0] na, nb, output reg snan, qnan, inf, zero, subnormal, normal);

    wire Asnan, Aqnan, Ainf, Azero, Asubnormal, Anormal;
    wire Bsnan, Bqnan, Binf, Bzero, Bsubnormal, Bnormal;
    reg [15:0] productoTemp, product;
    reg [15:0] Signo;
    Fp_clasifier A(na, Asnan, Aqnan, Ainf, Azero, Asubnormal, Anormal);
    Fp_clasifier B(nb, Bsnan, Bqnan, Binf, Bzero, Bsubnormal, Bnormal);

    reg [21:0] partialResult; 
    reg [4:0] expa;
    reg [4:0] expb;
    parameter bias = 15; 
    reg [5:0] exponent;

    always @(*) begin
        {snan, qnan, inf, zero, subnormal, normal} = 6'b0;
        Signo = na[15] ^ nb[15];

        if (Asnan | Bsnan) begin
            productoTemp = Asnan ? na : nb;
            snan = 1;
        end else if (Aqnan | Bqnan) begin
            productoTemp = Aqnan ? na : nb;
            qnan = 1;
        end else if (Ainf | Binf) begin
            if (Azero | Bzero) begin
                productoTemp = {Signo, {5{1'b1}}, 1'b1, 9'b1};
                qnan = 1;
            end else begin
                productoTemp = {Signo, {5{1'b1}}, 10'b0};
                inf = 1;
            end
        end else if (Azero | Bzero || (Asubnormal & Bsubnormal)) begin
            productoTemp = {Signo, 15'b0};
            zero = 1;
        end else begin
            expa = na[14:10] - bias;
            expb = nb[14:10] - bias;
            exponent = expa + expb + bias; // Corregido para sumar el bias después de la suma de los exponentes
            partialResult = {1'b1, na[9:0]} * {1'b1, nb[9:0]};

            if (partialResult[21]) begin
                partialResult = partialResult >> 1
                ;
                exponent = exponent + 1;
            end

            if (exponent > 30) begin // Corregido para considerar el rango correcto del exponente
                productoTemp = {Signo, 5'b11111, 10'b0};
                inf = 1;
            end else if (exponent < 1) begin // Corregido para el rango inferior del exponente
                productoTemp = {Signo, 15'b0};
                zero = 1;
            end else begin
                productoTemp = {Signo, exponent[4:0], partialResult[19:10]}; // Ajustado para seleccionar los bits correctos de partialResult
                normal = 1; 
            end
        end
    end

    assign producto = productoTemp; // Asigna productoTemp a la salida producto
endmodule





module button_counter(output wire [15:0] producto, input   clk , rst  , NEXT);

reg [2:0] state , next_state;
reg [31:0] counter;
parameter hold =2'b00 , pressed_buttom = 2'b01 , released_buttom = 2'b10;
wire [15:0] A , B ;
wire snan, qnan, inf, zero, subnormal, normal;

memo OPERANDS_REGISTER(clk , rst , counter , A , B );
FP_mul MULTIPLICA(.producto(producto),.na(A) , .nb(B)  , .snan(snan) , .qnan(qnan) , .inf(inf) , .zero(zero) , .subnormal(subnormal) , .normal(normal));

always @*
begin

case(state)

hold: begin
    if(NEXT) next_state = pressed_buttom;
    else next_state = hold;
end
pressed_buttom :  begin
    if(!NEXT) next_state = released_buttom;
    else next_state = pressed_buttom;
    end
released_buttom: begin
    if(NEXT) next_state = hold;
else next_state = released_buttom;
end
endcase



end



always @(posedge clk , posedge rst)
begin

if(rst) begin
 counter<=0;
 state<=hold;
end
else begin
state<=next_state;
if(state== pressed_buttom && next_state == released_buttom)
 counter<=counter+1;
  

end


end



endmodule

calculations_tb.v

module button_counter_tb;

    // Entradas
    reg clk;
    reg rst;
    reg NEXT;

    // Salidas
    wire [15:0] producto;

    // Instancia del módulo a probar
    button_counter uut (
        .producto(producto), 
        .clk(clk), 
        .rst(rst), 
        .NEXT(NEXT)
    );

    // Generación de la señal de reloj
    initial begin
        clk = 0;
        forever #10 clk = ~clk; // Cambia el estado cada 10 ns
    end

    // Proceso de prueba
    initial begin
        $dumpfile("counter.vcd");
        $dumpvars(0,button_counter_tb);
        // Inicialización
        rst = 1;
        NEXT = 0;

        // Reinicio del sistema
        #20;
        rst = 0;

        // Simula el botón presionado
        #30 NEXT = 1;
        #20 NEXT = 0;

        // Simula el botón presionado de nuevo
        #40 NEXT = 1;
        #20 NEXT = 0;

        // Simula el botón presionado una vez más
        #50 NEXT = 1;
        #20 NEXT = 0;

        // Finaliza la simulación
        #100 $finish;
    end
      
endmodule

counter.vcd
$date
	Thu Nov 23 14:34:38 2023
$end
$version
	Icarus Verilog
$end
$timescale
	1s
$end
$scope module button_counter_tb $end
$var wire 16 ! producto [15:0] $end
$var reg 1 " NEXT $end
$var reg 1 # clk $end
$var reg 1 $ rst $end
$scope module uut $end
$var wire 1 " NEXT $end
$var wire 1 # clk $end
$var wire 1 $ rst $end
$var wire 1 % zero $end
$var wire 1 & subnormal $end
$var wire 1 ' snan $end
$var wire 1 ( qnan $end
$var wire 16 ) producto [15:0] $end
$var wire 1 * normal $end
$var wire 1 + inf $end
$var wire 16 , B [15:0] $end
$var wire 16 - A [15:0] $end
$var reg 32 . counter [31:0] $end
$var reg 3 / next_state [2:0] $end
$var reg 3 0 state [2:0] $end
$scope module MULTIPLICA $end
$var wire 16 1 producto [15:0] $end
$var wire 16 2 nb [15:0] $end
$var wire 16 3 na [15:0] $end
$var wire 1 4 Bzero $end
$var wire 1 5 Bsubnormal $end
$var wire 1 6 Bsnan $end
$var wire 1 7 Bqnan $end
$var wire 1 8 Bnormal $end
$var wire 1 9 Binf $end
$var wire 1 : Azero $end
$var wire 1 ; Asubnormal $end
$var wire 1 < Asnan $end
$var wire 1 = Aqnan $end
$var wire 1 > Anormal $end
$var wire 1 ? Ainf $end
$var reg 16 @ Signo [15:0] $end
$var reg 5 A expa [4:0] $end
$var reg 5 B expb [4:0] $end
$var reg 6 C exponent [5:0] $end
$var reg 1 + inf $end
$var reg 1 * normal $end
$var reg 22 D partialResult [21:0] $end
$var reg 16 E productoTemp [15:0] $end
$var reg 1 ( qnan $end
$var reg 1 ' snan $end
$var reg 1 & subnormal $end
$var reg 1 % zero $end
$scope module A $end
$var wire 1 ? inf $end
$var wire 1 > normal $end
$var wire 1 = qnan $end
$var wire 1 < snan $end
$var wire 1 ; subnormal $end
$var wire 1 : zero $end
$var wire 1 F sigZeroes $end
$var wire 16 G float [15:0] $end
$var wire 1 H expZeroes $end
$var wire 1 I expOnes $end
$upscope $end
$scope module B $end
$var wire 1 9 inf $end
$var wire 1 8 normal $end
$var wire 1 7 qnan $end
$var wire 1 6 snan $end
$var wire 1 5 subnormal $end
$var wire 1 4 zero $end
$var wire 1 J sigZeroes $end
$var wire 16 K float [15:0] $end
$var wire 1 L expZeroes $end
$var wire 1 M expOnes $end
$upscope $end
$upscope $end
$scope module OPERANDS_REGISTER $end
$var wire 32 N a [31:0] $end
$var wire 1 # clk $end
$var wire 1 $ rst $end
$var reg 16 O ra [15:0] $end
$var reg 16 P rb [15:0] $end
$upscope $end
$upscope $end
$upscope $end
$enddefinitions $end
#0
$dumpvars
b100001000000000 P
b100000000000000 O
b0 N
0M
0L
b100001000000000 K
0J
0I
0H
b100000000000000 G
1F
b100011000000000 E
b110000000000000000000 D
b10001 C
b1 B
b1 A
b0 @
0?
1>
0=
0<
0;
0:
09
18
07
06
05
04
b100000000000000 3
b100001000000000 2
b100011000000000 1
b0 0
b0 /
b0 .
b100000000000000 -
b100001000000000 ,
0+
1*
b100011000000000 )
0(
0'
0&
0%
1$
0#
0"
b100011000000000 !
$end
#10
1#
#20
0#
0$
#30
1#
#40
0#
#50
b1 0
b1 /
1#
1"
#60
0#
#70
0F
b100000100001111 !
b100000100001111 )
b100000100001111 1
b100000100001111 E
b101000011110101011100 D
b10000 C
b0 B
1*
b11110001100110 ,
b11110001100110 2
b11110001100110 K
b11110001100110 P
b100000010011010 -
b100000010011010 3
b100000010011010 G
b100000010011010 O
b1 .
b1 N
b10 0
b10 /
1#
0"
#80
0#
#90
1#
#100
0#
#110
b0 0
b1 /
1#
1"
#120
0#
#130
b0 /
1#
0"
#140
0#
#150
1#
#160
0#
#170
1#
#180
b1 /
0#
1"
#190
b1 0
1#
#200
b10 /
0#
0"
#210
0>
0'
0<
1?
1F
1I
1+
b111110000000000 !
b111110000000000 )
b111110000000000 1
b111110000000000 E
b100011001100000000000 D
b11111 C
b10000 A
0*
b111110000000000 -
b111110000000000 3
b111110000000000 G
b111110000000000 O
b10 .
b10 N
b10 0
1#
