Fsm_test.v


module Fp_clasifier
(input [15:0] float , 
output snan , qnan , inf , zero , subnormal , normal );

wire expOnes , expZeroes , sigZeroes ; 

assign expOnes = &float[14:10];
assign expZeroes = ~|float[14:10];
assign sigZeroes = ~|float[9:0];

assign snan = expOnes & ~sigZeroes & ~float[9];
assign qnan = expOnes & float[9];
assign inf  = expOnes & sigZeroes;
assign zero = expZeroes & sigZeroes;
assign subnormal = expZeroes & ~sigZeroes;
assign normal = ~expOnes &  ~expZeroes;

endmodule

module FP_mul(output wire [15:0] producto, input [15:0] na, nb, output reg snan, qnan, inf, zero, subnormal, normal);

    wire Asnan, Aqnan, Ainf, Azero, Asubnormal, Anormal;
    wire Bsnan, Bqnan, Binf, Bzero, Bsubnormal, Bnormal;
    reg [15:0] productoTemp, product;
    reg [15:0] Signo;
    Fp_clasifier A(na, Asnan, Aqnan, Ainf, Azero, Asubnormal, Anormal);
    Fp_clasifier B(nb, Bsnan, Bqnan, Binf, Bzero, Bsubnormal, Bnormal);

    reg [21:0] partialResult; 
    reg [4:0] expa;
    reg [4:0] expb;
    parameter bias = 15; 
    reg [5:0] exponent;

    always @(*) begin
        {snan, qnan, inf, zero, subnormal, normal} = 6'b0;
        Signo = na[15] ^ nb[15];

        if (Asnan | Bsnan) begin
            productoTemp = Asnan ? na : nb;
            snan = 1;
        end else if (Aqnan | Bqnan) begin
            productoTemp = Aqnan ? na : nb;
            qnan = 1;
        end else if (Ainf | Binf) begin
            if (Azero | Bzero) begin
                productoTemp = {Signo, {5{1'b1}}, 1'b1, 9'b1};
                qnan = 1;
            end else begin
                productoTemp = {Signo, {5{1'b1}}, 10'b0};
                inf = 1;
            end
        end else if (Azero | Bzero || (Asubnormal & Bsubnormal)) begin
            productoTemp = {Signo, 15'b0};
            zero = 1;
        end else begin
            expa = na[14:10] - bias;
            expb = nb[14:10] - bias;
            exponent = expa + expb + bias; // Corregido para sumar el bias después de la suma de los exponentes
            partialResult = {1'b1, na[9:0]} * {1'b1, nb[9:0]};

            if (partialResult[21]) begin
                partialResult = partialResult >> 1
                ;
                exponent = exponent + 1;
            end

            if (exponent > 30) begin // Corregido para considerar el rango correcto del exponente
                productoTemp = {Signo, 5'b11111, 10'b0};
                inf = 1;
            end else if (exponent < 1) begin // Corregido para el rango inferior del exponente
                productoTemp = {Signo, 15'b0};
                zero = 1;
            end else begin
                productoTemp = {Signo, exponent[4:0], partialResult[19:10]}; // Ajustado para seleccionar los bits correctos de partialResult
                normal = 1; 
            end
        end
    end

    assign producto = productoTemp; // Asigna productoTemp a la salida producto
endmodule


module Fp_mul_fsm(output reg [15:0] producto, input [15:0] na,input   clk , rst  , SAVE);

wire qnan, inf, zero, subnormal, normal;
reg [1:0 ]state , next_state;
parameter save_a = 2'b00 , save_b=2'b01 , save_none = 2'b11  ;
reg [15:0]  current_a , current_b ;
wire[15:0] product;
FP_mul mod(.producto(product), .na(current_a) , .nb(current_b)  , .snan(snan) , .qnan(qnan) , .inf(inf) , .zero(zero) , .subnormal(subnormal) , .normal(normal));

//next stage logic O TUTORIAL PARA RODRIGO

always @*  //Pones el valor de a en los switches , SAVE  --> estaras guardando ese valor y pasaras al valor de save B (lo q tengas puesto ahi se estara guardando) una vez presionas SAVE
//el valor de B se quedara pegado y debera mostrarse el valor en los leds

begin

case (state)

        save_a:
            if(SAVE) begin
                next_state = save_b;
                
            end
            else next_state =save_a;
        save_b: 
            if(SAVE) begin
               next_state= save_none;
            
            end
             else  begin next_state = save_b; end
    
        save_none:
            if(SAVE)
             next_state = save_a;
            else next_state = save_none;     
endcase



end 

// Lógica secuencial para el manejo de estados y registros
    always @(posedge clk or posedge rst) begin
        if (rst) begin
            state <= save_none;
            current_a <= 0;
            current_b <= 0;
        end else begin
     
            if (state == save_none && next_state == save_a) begin
                current_a <= na;
            end
            if (state == save_a && next_state == save_b) begin
                current_b <= na;
            end

                   state <= next_state;
        end
    end

    // Lógica de salida
    always @* begin
        case (state)
            save_a: producto = current_a;
            save_b: producto = current_b;
            save_none: producto = product;
            default: producto = 16'b0;
        endcase
    end
        
endmodule

Fsm_test_tb.v

module Fp_mul_fsm_tb;

    reg [15:0] na, nb;
    reg clk, rst, SAVE;
    wire [15:0] producto;
    wire snan, qnan, inf, zero, subnormal, normal;

    // Instancia del módulo Fp_mul_fsm
    Fp_mul_fsm uut (
        .producto(producto),
        .na(na),
        .clk(clk),
        .rst(rst),
        .SAVE(SAVE) 
    );

    // Generación del reloj
    always #5 clk = ~clk;  // Cambia cada 5 ns, frecuencia = 100 MHz

    // Test
    initial begin
        $dumpfile("Mul3.vcd");
        $dumpvars(0,Fp_mul_fsm_tb);
        // Inicialización
        clk = 0;
        rst = 1;
        SAVE = 0; 
        #2
        na = 16'h4000; // 2
        SAVE = 1; //pasas al estado para guardar A
        rst =0;
        #1
        // Cargar valores de prueba
        rst = 0;
         SAVE =0; // No se esta guardando esto te permite ingresar A 
         #10
           SAVE = 1;    // Guardar A --> pasas a estado guardar b
         #10
        SAVE = 0; //A se holdea y no se guarda lo que pongas en B , aca puedes ingresar el valor de B
        na = 16'h4200; // 3
        #10
        SAVE = 1;      // Guardar B y pasas a calcular se mostrara el valor de producto estaras en el estado de save_none
        #10;
            SAVE =0; //No cambias y se va a mostrar el resultado
             na = 16'h5FD1;//ESTE VALOR SE GUARDA EN A
            #10
            SAVE =1; //pasar a estado guardar A 
            #10
            na = 16'h5BAD; //ESTE VALOR SE GUARDA EN B
            SAVE = 0;
            #10
             SAVE =1;//pasar a guardar B 
             #10
             SAVE=0;// ACA DEBERIA MOSTRARSE EL RESULTADO
             #10
        $finish;
    end

endmodule

Mul3.vcd
$date
	Wed Nov 22 02:26:49 2023
$end
$version
	Icarus Verilog
$end
$timescale
	1s
$end
$scope module Fp_mul_fsm_tb $end
$var wire 16 ! producto [15:0] $end
$var reg 1 " SAVE $end
$var reg 1 # clk $end
$var reg 16 $ na [15:0] $end
$var reg 1 % rst $end
$scope module uut $end
$var wire 1 " SAVE $end
$var wire 1 # clk $end
$var wire 16 & na [15:0] $end
$var wire 1 % rst $end
$var wire 1 ' zero $end
$var wire 1 ( subnormal $end
$var wire 1 ) snan $end
$var wire 1 * qnan $end
$var wire 16 + product [15:0] $end
$var wire 1 , normal $end
$var wire 1 - inf $end
$var reg 16 . current_a [15:0] $end
$var reg 16 / current_b [15:0] $end
$var reg 2 0 next_state [1:0] $end
$var reg 16 1 producto [15:0] $end
$var reg 2 2 state [1:0] $end
$scope module mod $end
$var wire 16 3 na [15:0] $end
$var wire 16 4 nb [15:0] $end
$var wire 16 5 producto [15:0] $end
$var wire 1 6 Bzero $end
$var wire 1 7 Bsubnormal $end
$var wire 1 8 Bsnan $end
$var wire 1 9 Bqnan $end
$var wire 1 : Bnormal $end
$var wire 1 ; Binf $end
$var wire 1 < Azero $end
$var wire 1 = Asubnormal $end
$var wire 1 > Asnan $end
$var wire 1 ? Aqnan $end
$var wire 1 @ Anormal $end
$var wire 1 A Ainf $end
$var reg 16 B Signo [15:0] $end
$var reg 5 C expa [4:0] $end
$var reg 5 D expb [4:0] $end
$var reg 6 E exponent [5:0] $end
$var reg 1 - inf $end
$var reg 1 , normal $end
$var reg 22 F partialResult [21:0] $end
$var reg 16 G productoTemp [15:0] $end
$var reg 1 * qnan $end
$var reg 1 ) snan $end
$var reg 1 ( subnormal $end
$var reg 1 ' zero $end
$scope module A $end
$var wire 16 H float [15:0] $end
$var wire 1 A inf $end
$var wire 1 @ normal $end
$var wire 1 ? qnan $end
$var wire 1 > snan $end
$var wire 1 = subnormal $end
$var wire 1 < zero $end
$var wire 1 I sigZeroes $end
$var wire 1 J expZeroes $end
$var wire 1 K expOnes $end
$upscope $end
$scope module B $end
$var wire 16 L float [15:0] $end
$var wire 1 ; inf $end
$var wire 1 : normal $end
$var wire 1 9 qnan $end
$var wire 1 8 snan $end
$var wire 1 7 subnormal $end
$var wire 1 6 zero $end
$var wire 1 M sigZeroes $end
$var wire 1 N expZeroes $end
$var wire 1 O expOnes $end
$upscope $end
$upscope $end
$upscope $end
$upscope $end
$enddefinitions $end
#0
$dumpvars
0O
1N
1M
b0 L
0K
1J
1I
b0 H
b0 G
b100000000000000000000 F
b110001 E
b10001 D
b10001 C
b0 B
0A
0@
0?
0>
0=
1<
0;
0:
09
08
07
16
b0 5
b0 4
b0 3
b11 2
b0 1
b11 0
b0 /
b0 .
0-
0,
b0 +
0*
0)
0(
1'
bx &
1%
bx $
0#
0"
b0 !
$end
#2
b0 0
0%
1"
b100000000000000 $
b100000000000000 &
#3
b11 0
0"
#5
1#
#10
0#
#13
b0 0
1"
#15
1@
0<
b1 0
0J
1'
b100000000000000 !
b100000000000000 1
b0 2
b100000000000000 .
b100000000000000 3
b100000000000000 H
1#
#20
0#
#23
b0 0
b100001000000000 $
b100001000000000 &
0"
#25
1#
#30
0#
#33
b1 0
1"
#35
1:
1,
b100011000000000 +
b100011000000000 5
b100011000000000 G
b110000000000000000000 F
b10001 E
b1 D
b1 C
06
b11 0
0N
0M
0'
b100001000000000 !
b100001000000000 1
b1 2
b100001000000000 /
b100001000000000 4
b100001000000000 L
1#
#40
0#
#43
b1 0
0"
#45
1#
#50
0#
#53
b11 0
1"
#55
b100011000000000 !
b100011000000000 1
b0 0
b11 2
1#
#60
0#
#63
b11 0
0"
